tinkerhap/__init__.py
tinkerhap/tinkerhap.py
TinkerHap-1.0.0.dist-info/LICENSE.txt
TinkerHap-1.0.0.dist-info/METADATA
TinkerHap-1.0.0.dist-info/WHEEL
TinkerHap-1.0.0.dist-info/entry_points.txt
TinkerHap-1.0.0.dist-info/top_level.txt
TinkerHap-1.0.0.dist-info/RECORD
