Metadata-Version: 2.2
Name: TinkerHap
Version: 1.0.0
Author: Uri Hartmann
License: MIT
Classifier: Programming Language :: Python :: 3
Classifier: License :: OSI Approved :: MIT License
Classifier: Operating System :: OS Independent
Classifier: Topic :: Scientific/Engineering :: Bio-Informatics
Requires-Python: >=3.6.0
License-File: LICENSE.txt
Requires-Dist: pysam>=0.17.0
Dynamic: author
Dynamic: classifier
Dynamic: description
Dynamic: description-content-type
Dynamic: license
Dynamic: requires-dist
Dynamic: requires-python
